phenotron/__init__.py
phenotron/cli.py
phenotron/excel_transform.py
phenotron/output.py
phenotron/validate.py
phenotron-0.1.0.dist-info/METADATA
phenotron-0.1.0.dist-info/WHEEL
phenotron-0.1.0.dist-info/entry_points.txt
phenotron-0.1.0.dist-info/RECORD
