Metadata-Version: 2.1
Name: phenotron
Version: 0.1.0
Summary: 
License: MIT
Keywords: phenopackets,hpo,library,cli,transform
Author: Michael Gargano
Author-email: Michael.Gargano@jax.org
Requires-Python: >=3.11,<4.0
Classifier: License :: OSI Approved :: MIT License
Classifier: Programming Language :: Python :: 3
Classifier: Programming Language :: Python :: 3.11
Requires-Dist: click (>=8.1.6,<9.0.0)
Requires-Dist: hpo-toolkit (>=0.2.0,<0.3.0)
Requires-Dist: pyphetools (>=0.4.8,<0.5.0)
